LICENSE
MANIFEST.in
README.rst
Readme.rst
distribute_setup.py
setup.cfg
setup.py
jip/__init__.py
jip/cluster.py
jip/configuration.py
jip/db.py
jip/executils.py
jip/grids.py
jip/jobs.py
jip/logger.py
jip/options.py
jip/parser.py
jip/pipelines.py
jip/profiler.py
jip/profiles.py
jip/tempfiles.py
jip/templates.py
jip/tools.py
jip/utils.py
jip/cli/__init__.py
jip/cli/jip_archive.py
jip/cli/jip_bash.py
jip/cli/jip_cancel.py
jip/cli/jip_check.py
jip/cli/jip_clean.py
jip/cli/jip_delete.py
jip/cli/jip_edit.py
jip/cli/jip_exec.py
jip/cli/jip_hold.py
jip/cli/jip_interpreter.py
jip/cli/jip_jobs.py
jip/cli/jip_logs.py
jip/cli/jip_main.py
jip/cli/jip_pipe.py
jip/cli/jip_profiles.py
jip/cli/jip_restart.py
jip/cli/jip_run.py
jip/cli/jip_server.py
jip/cli/jip_show.py
jip/cli/jip_specs.py
jip/cli/jip_submit.py
jip/cli/jip_tools.py
jip/dispatcher/jip_binding.c
jip/dispatcher/jip_dispatcher.c
jip/dispatcher/jip_dispatcher.h
jip/scripts/__init__.py
jip/vendor/__init__.py
jip/vendor/docopt.py
jip/vendor/texttable.py
pyjip.egg-info/PKG-INFO
pyjip.egg-info/SOURCES.txt
pyjip.egg-info/dependency_links.txt
pyjip.egg-info/entry_points.txt
pyjip.egg-info/requires.txt
pyjip.egg-info/top_level.txt
test/test_api.py
test/test_cli.py
test/test_cluster.py
test/test_config.py
test/test_db.py
test/test_embedded_tools.py
test/test_examples.py
test/test_executils.py
test/test_jip_exec.py
test/test_job_environments.py
test/test_jobs.py
test/test_local_cluster.py
test/test_options.py
test/test_pickler.py
test/test_pipelines.py
test/test_profiles.py
test/test_script_parser.py
test/test_templates.py
test/test_tools.py
test/test_utils.py