Metadata-Version: 1.0
Name: pyjip
Version: 0.6
Summary: JIP pipeline library
Home-page: UNKNOWN
Author: UNKNOWN
Author-email: thasso.griebel@gmail.com
License: BSD
Platform: UNKNOWN
